cmipld/__init__.py
cmipld/cli.py
cmipld/gettest.py
cmipld/import_graph.pdf
cmipld/locations.py
cmipld/prefix_mappings.json
cmipld/version.py
cmipld/copier/__init__.py
cmipld/copier/project/copier.yml
cmipld/cvs/__init__.py
cmipld/cvs/cmip6plus.py
cmipld/cvs/generate.py
cmipld/cvs/parse.py
cmipld/cvs/review.ipynb
cmipld/generate/__init__.py
cmipld/generate/create_readme.py
cmipld/generate/elastic.ipynb
cmipld/generate/elasticmipcvs.py
cmipld/generate/generate_summary.py
cmipld/generate/git_coauthor_demo.py.bak
cmipld/generate/legacy.zip
cmipld/generate/new_issue.py
cmipld/generate/update_all.py
cmipld/generate/update_ctx.py
cmipld/generate/validate_json.py
cmipld/generate/validate_json_with_coauthors.py.bak
cmipld/generate/issue-template/test.ipynb
cmipld/misc/graph.pdf
cmipld/misc/import_graph.dot
cmipld/misc/legacy.zip
cmipld/misc/pycallgraph.png
cmipld/misc/scalpel.ipynb
cmipld/scripts/development/coauthor_file
cmipld/scripts/directory-utilities/dev
cmipld/scripts/directory-utilities/ld2graph
cmipld/scripts/directory-utilities/validjsonld
cmipld/scripts/jsonld-util/rmbak
cmipld/scripts/jsonld-util/rmgraph
cmipld/tests/__init__.py
cmipld/tests/inputs.py
cmipld/tests/legacy.zip
cmipld/tests/cvs/conftest.py
cmipld/tests/cvs/cvfile_test.py
cmipld/tests/jsonld/__init__.py
cmipld/tests/jsonld/EMD/sample.ipynb
cmipld/tests/jsonld/components/README.md
cmipld/tests/jsonld/components/__init__.py
cmipld/tests/jsonld/components/check_exists.py
cmipld/tests/jsonld/components/date.py
cmipld/tests/jsonld/components/description.py
cmipld/tests/jsonld/components/id.py
cmipld/tests/jsonld/components/stringcheck.py
cmipld/tests/jsonld/components/type.py
cmipld/tests/jsonld/experiment/__init__.py
cmipld/tests/jsonld/organisation/__init__.py
cmipld/tests/jsonld/organisation/ror.py
cmipld/utils/__init__.py
cmipld/utils/checksum.py
cmipld/utils/io.py
cmipld/utils/jsontools.py
cmipld/utils/ld2graph.py.bak
cmipld/utils/ldparse.py
cmipld/utils/sanitiser.py
cmipld/utils/shell_wrappers.py
cmipld-0.0.6.dist-info/METADATA
cmipld-0.0.6.dist-info/WHEEL
cmipld-0.0.6.dist-info/entry_points.txt
cmipld-0.0.6.dist-info/top_level.txt
cmipld-0.0.6.dist-info/RECORD
